dapplooker/__init__.py
dapplooker/chart_constants.py
dapplooker/dapplooker_charts.py
dapplooker/interface.py
dapplooker-0.0.3.dist-info/LICENSE
dapplooker-0.0.3.dist-info/METADATA
dapplooker-0.0.3.dist-info/WHEEL
dapplooker-0.0.3.dist-info/top_level.txt
dapplooker-0.0.3.dist-info/RECORD
